meillionen/.gitignore
meillionen/__init__.py
meillionen/client.py
meillionen/exceptions.py
meillionen/interface/_ClassInterface.py
meillionen/interface/_FunctionInterface.py
meillionen/interface/_MethodRequest.py
meillionen/interface/_ModuleInterface.py
meillionen/interface/_Mutability.py
meillionen/interface/_Resource.py
meillionen/interface/_Schema.py
meillionen/interface/__init__.py
meillionen/interface/base.py
meillionen/interface/class_interface.py
meillionen/interface/method_interface.py
meillionen/interface/method_request.py
meillionen/interface/module_interface.py
meillionen/interface/mutability.py
meillionen/interface/resource.py
meillionen/interface/schema.py
meillionen/response.py
meillionen/server.py
meillionen/settings.py
meillionen-0.1.4.dist-info/WHEEL
meillionen-0.1.4.dist-info/METADATA
meillionen-0.1.4.dist-info/RECORD
