Metadata-Version: 2.1
Name: meillionen
Version: 0.1.4
Summary: A model interface serialization and rpc framework
Home-page: https://github.com/openmodelingfoundation/meillionen
License: MIT
Author: Calvin Pritchard
Author-email: calvin.pritchard@asu.edu
Requires-Python: >=3.8,<4.0
Classifier: License :: OSI Approved :: MIT License
Classifier: Programming Language :: Python :: 3
Classifier: Programming Language :: Python :: 3.10
Classifier: Programming Language :: Python :: 3.8
Classifier: Programming Language :: Python :: 3.9
Provides-Extra: prefect
Requires-Dist: flatbuffers (>=2.0,<3.0)
Requires-Dist: landlab (>=2.3.0,<3.0.0)
Requires-Dist: netCDF4 (>=1.5.7,<2.0.0)
Requires-Dist: prefect (>=0.15.6,<0.16.0); extra == "prefect"
Requires-Dist: pyarrow (>=5.0.0,<6.0.0)
Requires-Dist: pydantic (>=1.8.2,<2.0.0)
Requires-Dist: sh (>=1.14.2,<2.0.0)
Requires-Dist: xarray (>=0.19.0,<0.20.0)
Project-URL: Documentation, https://openmodelingfoundation.github.io/meillionen
